abottle
