Metadata-Version: 2.1
Name: abottle
Version: 0.0.15
Summary: put your model into **a bottle** then you get a working server and more.
Home-page: UNKNOWN
Author: taylorhere
Author-email: taylorherelee@gmail.com
License: UNKNOWN
Platform: UNKNOWN
Requires-Python: <3.10
